bert_base/__init__.py
bert_base/bert/__init__.py
bert_base/bert/create_pretraining_data.py
bert_base/bert/extract_features.py
bert_base/bert/modeling.py
bert_base/bert/modeling_test.py
bert_base/bert/optimization.py
bert_base/bert/optimization_test.py
bert_base/bert/run_classifier.py
bert_base/bert/run_pretraining.py
bert_base/bert/run_squad.py
bert_base/bert/tokenization.py
bert_base/bert/tokenization_test.py
bert_base/client/__init__.py
bert_base/runs/__init__.py
bert_base/server/__init__.py
bert_base/server/graph.py
bert_base/server/helper.py
bert_base/server/http.py
bert_base/server/zmq_decor.py
bert_base/train/__init__.py
bert_base/train/bert_lstm_ner.py
bert_base/train/conlleval.py
bert_base/train/lstm_crf_layer.py
bert_base/train/models.py
bert_base/train/tf_metrics.py
bert_base/train/train_helper.py
bert_base-0.0.9.dist-info/METADATA
bert_base-0.0.9.dist-info/WHEEL
bert_base-0.0.9.dist-info/entry_points.txt
bert_base-0.0.9.dist-info/top_level.txt
bert_base-0.0.9.dist-info/RECORD
