Metadata-Version: 2.1
Name: bert-base
Version: 0.0.9
Summary: Use Google's BERT for Chinese natural language processing tasks such as named entity recognition and provide server services
Home-page: https://github.com/macanv/BERT-BiLSTM-CRF-NER
Author: Ma Can
Author-email: ma_cancan@163.com
License: MIT
Keywords: bert nlp ner NER named entity recognition bilstm crf tensorflow machine learning sentence encoding embedding serving
Platform: UNKNOWN
Classifier: Programming Language :: Python :: 3.6
Classifier: License :: OSI Approved :: MIT License
Classifier: Operating System :: OS Independent
Requires-Dist: numpy
Requires-Dist: six
Requires-Dist: pyzmq (>=16.0.0)
Requires-Dist: GPUtil (>=1.3.0)
Requires-Dist: termcolor (>=1.1)
Provides-Extra: cpu
Requires-Dist: tensorflow (>=1.10.0) ; extra == 'cpu'
Provides-Extra: gpu
Requires-Dist: tensorflow-gpu (>=1.10.0) ; extra == 'gpu'
Provides-Extra: http
Requires-Dist: flask ; extra == 'http'
Requires-Dist: flask-compress ; extra == 'http'
Requires-Dist: flask-cors ; extra == 'http'
Requires-Dist: flask-json ; extra == 'http'
